sdcp_printer/__init__.py
sdcp_printer/async_udp.py
sdcp_printer/enum.py
sdcp_printer/message.py
sdcp_printer/request.py
sdcp_printer/scanner.py
sdcp_printer-0.4.1.dist-info/licenses/LICENSE
sdcp_printer-0.4.1.dist-info/METADATA
sdcp_printer-0.4.1.dist-info/WHEEL
sdcp_printer-0.4.1.dist-info/top_level.txt
sdcp_printer-0.4.1.dist-info/RECORD
