Metadata-Version: 2.4
Name: sdcp_printer
Version: 0.4.1
Summary: API to communicate with 3D printers using the SDCP protocol.
Author-email: Kevin Petersen <kevinvkpetersen@gmail.com>
Project-URL: Homepage, https://github.com/kevinvkpetersen/sdcp-printer-api
Project-URL: Issues, https://github.com/kevinvkpetersen/sdcp-printer-api/issues
Classifier: Programming Language :: Python :: 3
Classifier: License :: OSI Approved :: MIT License
Classifier: Operating System :: OS Independent
Requires-Python: >=3.11
License-File: LICENSE
Requires-Dist: asyncio-dgram
Requires-Dist: websockets
Dynamic: license-file
